day_3/full_adder/full_adder_p.v
module full_adder (x, y, c_in, s, c_out);
  input x, y, c_in;
  output s,c_out;
  wire w1, w2, w3, w4;

  xor g1(w1, x, y);
  xor g2(s, w1, c_in);
  and g3(w2, x, y);
  and g4(w3, x, y);
  and g5(w4, y, c_in);
  or g6(c_out, w2, w3, w4);
endmodule

day_3/full_adder/FULL_ADDER_TB.v
module full_adder_tb;
reg x, y, c_in;
wire s, c_out;
 
 full_adder fa(
    .x(x),
    .y(y),
    .c_in(c_in),
    .s(s),
    .c_out(c_out)
  );
     initial begin
    $dumpfile("full_adder_tb.vcd");
    $dumpvars;
    $monitor("At time %0t: x=%b y=%b c_in=%b s=%b c_out=%b", $time,x,y,c_in,s,c_out);
    

    x = 0; y = 0; c_in =0; #10;
    x = 0; y = 0; c_in =1; #10;
    x = 0; y = 1; c_in =0; #10;
    x = 0; y = 1; c_in =1; #10;
    x = 1; y = 0; c_in =0; #10;
    x = 1; y = 0; c_in =1; #10;
    x = 1; y = 1; c_in =0; #10;
    x = 1; y = 1; c_in =1; #10;

   
    $finish;
  end
endmodule

day_3/full_adder/full_adder_tb.vcd
$date
	Fri Jul 04 12:57:11 2025
$end
$version
	Icarus Verilog
$end
$timescale
	1s
$end
$scope module full_adder_tb $end
$var wire 1 ! s $end
$var wire 1 " c_out $end
$var reg 1 # c_in $end
$var reg 1 $ x $end
$var reg 1 % y $end
$scope module fa $end
$var wire 1 # c_in $end
$var wire 1 " c_out $end
$var wire 1 ! s $end
$var wire 1 & w1 $end
$var wire 1 ' w2 $end
$var wire 1 ( w3 $end
$var wire 1 ) w4 $end
$var wire 1 $ x $end
$var wire 1 % y $end
$upscope $end
$upscope $end
$enddefinitions $end
$comment Show the parameter values. $end
$dumpall
$end
#0
$dumpvars
0)
0(
0'
0&
0%
0$
0#
0"
0!
$end
#10
1!
1#
#20
1&
0#
1%
#30
1"
0!
1)
1#
#40
0"
1!
0)
0#
0%
1$
#50
0!
1#
#60
1"
0&
1'
1(
0#
1%
#70
1!
1)
1#
