day_3/full_subtractor/full_subtractor_p.v
module full_subtractor(input a, b, B_in, output D, B_out);
  assign D = a ^ b ^ B_in;
  assign B_out = (~a & b) | (~(a ^ b) & B_in);
endmodule

day_3/full_subtractor/tb_full_subtractor.v
module tb_full_subtractor;
  reg a, b, B_in;
  wire D, B_out;
  
  full_subtractor fs(a, b, B_in, D, B_out);
  
initial begin
  $monitor("At time %0t: a=%b b=%b, B_in=%b, difference=%b, borrow=%b",$time, a,b,B_in,D,B_out);
  $dumpfile ("tb_full_subtractor.vcd");
  $dumpvars;
  
    a = 0; b = 0; B_in = 0; #1;
    a = 0; b = 0; B_in = 1; #1;
    a = 0; b = 1; B_in = 0; #1;
    a = 0; b = 1; B_in = 1; #1;
    a = 1; b = 0; B_in = 0; #1;
    a = 1; b = 0; B_in = 1; #1;
    a = 1; b = 1; B_in = 0; #1;
    a = 1; b = 1; B_in = 1;
  end
endmodule

day_3/full_subtractor/tb_full_subtractor.vcd
$date
	Fri Jul 04 14:55:14 2025
$end
$version
	Icarus Verilog
$end
$timescale
	1s
$end
$scope module tb_full_subtractor $end
$var wire 1 ! D $end
$var wire 1 " B_out $end
$var reg 1 # B_in $end
$var reg 1 $ a $end
$var reg 1 % b $end
$scope module fs $end
$var wire 1 # B_in $end
$var wire 1 " B_out $end
$var wire 1 ! D $end
$var wire 1 $ a $end
$var wire 1 % b $end
$upscope $end
$upscope $end
$enddefinitions $end
$comment Show the parameter values. $end
$dumpall
$end
#0
$dumpvars
0%
0$
0#
0"
0!
$end
#1
1"
1!
1#
#2
0#
1%
#3
0!
1#
#4
0"
1!
0#
0%
1$
#5
0!
1#
#6
0#
1%
#7
1"
1!
1#
